[
    {
      "name": "Oak Avenue",
      "city": "Kolkata",
      "state": "WB",
      "country": "India",
      "type": "house",
      "fare": 2500,
      "availableFrom": "2023-11-30T14:28:23.847Z",
      "bed": 3,
      "bathroom": 2,
      "length": 35,
      "width": 15,
      "img": "https://example.com/hotel1.jpg",
      "owner": "655db5c4432485f1e7330076"
    },
    {
      "name": "Maple Street",
      "city": "Delhi",
      "state": "DL",
      "country": "India",
      "type": "apartment",
      "fare": 1200,
      "availableFrom": "2023-12-05T09:42:11.528Z",
      "bed": 2,
      "bathroom": 1,
      "length": 25,
      "width": 10,
      "img": "https://example.com/hotel2.jpg",
      "owner": "655db5c4432485f1e7330076"
    },
    {
      "name": "Pine Lane",
      "city": "Jalpaiguri",
      "state": "WB",
      "country": "India",
      "type": "condo",
      "fare": 1800,
      "availableFrom": "2023-12-10T18:15:33.302Z",
      "bed": 1,
      "bathroom": 1,
      "length": 20,
      "width": 12,
      "img": "https://example.com/hotel3.jpg",
      "owner": "655db5c4432485f1e7330076"
    },
    {
      "name": "Elm Street",
      "city": "Diamond",
      "state": "WB",
      "country": "India",
      "type": "townhouse",
      "fare": 3000,
      "availableFrom": "2023-12-15T11:55:45.761Z",
      "bed": 4,
      "bathroom": 3,
      "length": 40,
      "width": 18,
      "img": "https://example.com/hotel4.jpg",
      "owner": "655db5c4432485f1e7330076"
    },
    {
      "name": "Birch Road",
      "city": "Kolkata",
      "state": "WB",
      "country": "India",
      "type": "other",
      "fare": 2000,
      "availableFrom": "2023-12-20T22:10:55.924Z",
      "bed": 3,
      "bathroom": 2,
      "length": 30,
      "width": 14,
      "img": "https://example.com/hotel5.jpg",
      "owner": "655db5c4432485f1e7330076"
    },
    {
      "name": "Royal Residency",
      "city": "Delhi",
      "state": "DL",
      "country": "India",
      "type": "apartment",
      "fare": 1500,
      "availableFrom": "2023-12-25T14:00:00.000Z",
      "bed": 2,
      "bathroom": 1,
      "length": 28,
      "width": 12,
      "img": "https://example.com/hotel6.jpg",
      "owner": "655db5c4432485f1e7330076"
    },
    {
      "name": "Green Meadows",
      "city": "Kolkata",
      "state": "WB",
      "country": "India",
      "type": "house",
      "fare": 2800,
      "availableFrom": "2023-12-30T12:30:00.000Z",
      "bed": 4,
      "bathroom": 3,
      "length": 40,
      "width": 20,
      "img": "https://example.com/hotel7.jpg",
      "owner": "655db5c4432485f1e7330076"
    },
    {
      "name": "City View Apartments",
      "city": "Delhi",
      "state": "DL",
      "country": "India",
      "type": "apartment",
      "fare": 1800,
      "availableFrom": "2024-01-05T10:15:00.000Z",
      "bed": 3,
      "bathroom": 2,
      "length": 32,
      "width": 15,
      "img": "https://example.com/hotel8.jpg",
      "owner": "655db5c4432485f1e7330076"
    }
  ]
  